Metadata-Version: 2.1
Name: test-logging
Version: 1.0.0
Summary: Read the latest Real Python tutorials
Home-page: https://gitlab.axiatadigitallabs.com/et/digital-telco/dte-telco/add-ons_creation/python/plugin-log
Author: testEmailClient1996
Author-email: testEmailClient1996@gmail.com
License: MIT
Platform: UNKNOWN
Classifier: License :: OSI Approved :: MIT License
Classifier: Programming Language :: Python :: 3
